{
  "verification_timestamp": "2026-02-12",
  "migration_file": "20260212000100_add_scraper_studio_tables.sql",
  "tables": {
    "scraper_config_test_skus": {
      "columns": [
        {"name": "id", "type": "uuid", "nullable": false, "default": "gen_random_uuid()"},
        {"name": "config_id", "type": "uuid", "nullable": false, "default": null},
        {"name": "sku", "type": "text", "nullable": false, "default": null},
        {"name": "sku_type", "type": "text", "nullable": false, "default": null},
        {"name": "added_by", "type": "uuid", "nullable": true, "default": null},
        {"name": "created_at", "type": "timestamp with time zone", "nullable": false, "default": "now()"}
      ],
      "foreign_keys": [
        {"column": "config_id", "references": "scraper_configs(id)", "on_delete": "CASCADE"}
      ],
      "constraints": [
        {"type": "CHECK", "definition": "sku_type IN ('test', 'fake', 'edge_case')"},
        {"type": "UNIQUE", "columns": ["config_id", "sku"]}
      ],
      "rls_policies": 5
    },
    "scraper_health_metrics": {
      "columns": [
        {"name": "id", "type": "uuid", "nullable": false, "default": "gen_random_uuid()"},
        {"name": "config_id", "type": "uuid", "nullable": false, "default": null},
        {"name": "metric_date", "type": "date", "nullable": false, "default": null},
        {"name": "total_runs", "type": "integer", "nullable": false, "default": "0"},
        {"name": "passed_runs", "type": "integer", "nullable": false, "default": "0"},
        {"name": "failed_runs", "type": "integer", "nullable": false, "default": "0"},
        {"name": "avg_duration_ms", "type": "integer", "nullable": true, "default": null},
        {"name": "top_failing_step", "type": "text", "nullable": true, "default": null},
        {"name": "selector_health", "type": "jsonb", "nullable": true, "default": "'{}'::jsonb"},
        {"name": "created_at", "type": "timestamp with time zone", "nullable": false, "default": "now()"},
        {"name": "updated_at", "type": "timestamp with time zone", "nullable": false, "default": "now()"}
      ],
      "foreign_keys": [
        {"column": "config_id", "references": "scraper_configs(id)", "on_delete": "CASCADE"}
      ],
      "constraints": [
        {"type": "UNIQUE", "columns": ["config_id", "metric_date"]}
      ],
      "rls_policies": 5
    }
  },
  "functions": [
    {
      "name": "update_health_metrics",
      "returns": "void",
      "security": "DEFINER",
      "description": "Aggregates daily health metrics from scraper_test_runs for trend analysis"
    },
    {
      "name": "update_health_metrics_updated_at",
      "returns": "trigger",
      "description": "Auto-updates updated_at column on row modification"
    }
  ],
  "status": "PASSED",
  "acceptance_criteria": {
    "test_sku_table": {
      "columns_correct": true,
      "foreign_key_to_scraper_configs": true,
      "sku_type_check_constraint": true,
      "rls_policies_exist": true
    },
    "health_metrics_table": {
      "columns_correct": true,
      "foreign_key_to_scraper_configs": true,
      "unique_constraint_config_date": true,
      "rls_policies_exist": true
    },
    "update_health_metrics_function": {
      "exists": true,
      "aggregates_last_30_days": true,
      "upsert_on_conflict": true
    }
  }
}
